setup.cfg
setup.py
json_traverse.egg-info/PKG-INFO
json_traverse.egg-info/SOURCES.txt
json_traverse.egg-info/dependency_links.txt
json_traverse.egg-info/top_level.txt
jsontraverse/__init__.py
jsontraverse/parser.py