Metadata-Version: 1.1
Name: json-traverse
Version: 0.2
Summary: Query complex JSON structures using a simple query syntax.
Home-page: https://github.com/EmilStenstrom/json-traverse/
Author: Emil Stenström
Author-email: em@kth.se
License: UNKNOWN
Download-URL: https://github.com/EmilStenstrom/json-traverse/archive/0.2.zip
Keywords: json,query,tree,parser,json-query
Platform: UNKNOWN
Classifier: Programming Language :: Python
Classifier: Programming Language :: Python :: 2
Classifier: Programming Language :: Python :: 2.7
Classifier: Programming Language :: Python :: 3
Classifier: Programming Language :: Python :: 3.3
Classifier: Programming Language :: Python :: 3.4
Classifier: Programming Language :: Python :: 3.5
Classifier: Operating System :: OS Independent
Classifier: Topic :: Utilities
